stitch_api/__init__.py
stitch_api/api_client.py
stitch_api/destination_types.py
stitch_api/destinations.py
stitch_api/jobs.py
stitch_api/notifications.py
stitch_api/source_types.py
stitch_api/sources.py
stitch_api/streams.py
stitch_api-1.0.0.dist-info/LICENSE
stitch_api-1.0.0.dist-info/METADATA
stitch_api-1.0.0.dist-info/WHEEL
stitch_api-1.0.0.dist-info/top_level.txt
stitch_api-1.0.0.dist-info/RECORD
