Metadata-Version: 2.1
Name: stitch-api
Version: 1.0.0
Summary: UNKNOWN
Home-page: https://github.com/Talend/stitch-api
Author: Thomas Bennett
Author-email: tbennett@talend.com
License: UNKNOWN
Platform: UNKNOWN
Classifier: Programming Language :: Python :: 3
Classifier: License :: OSI Approved :: GNU General Public License (GPL)
Classifier: Operating System :: OS Independent
Requires-Dist: requests
